KnowAlmost/__init__.py
KnowAlmost/main.py
KnowAlmost/setting.py
KnowAlmost/static/__init__.py
KnowAlmost/utils/__init__.py
KnowAlmost/utils/base.py
KnowAlmost/utils/error.py
KnowAlmost/utils/models.py
KnowAlmost/utils/parsers.py
KnowAlmost/utils/util.py
KnowAlmost-0.0.1.dist-info/LICENSE
KnowAlmost-0.0.1.dist-info/METADATA
KnowAlmost-0.0.1.dist-info/WHEEL
KnowAlmost-0.0.1.dist-info/top_level.txt
KnowAlmost-0.0.1.dist-info/RECORD
