Metadata-Version: 2.1
Name: KnowAlmost
Version: 0.0.1
Summary: KnowAlmost is a package that encapsulates the KnowAlmost api. I often use it in competitions and work. More skills are on the way!
Author: W·Wen
Author-email: W·Wen <23626319@qq.com>
License: MIT License        
Project-URL: Homepage, https://gitee.com/wu1wen/know-almost
Classifier: Programming Language :: Python :: 3
Classifier: License :: OSI Approved :: MIT License
Classifier: Operating System :: OS Independent
Requires-Python: >=3.7
License-File: LICENSE
Requires-Dist: loguru (==0.6.0)
Requires-Dist: PyExecJS (==1.5.1)
Requires-Dist: requests (==2.28.2)
